object_graph_streamer/__init__.py
object_graph_streamer/object_graph_streamer.py
object_graph_streamer/object_graph_streamer_test.py
object_graph_streamer/version.py
object_graph_streamer-0.0.1.dist-info/LICENSE
object_graph_streamer-0.0.1.dist-info/METADATA
object_graph_streamer-0.0.1.dist-info/WHEEL
object_graph_streamer-0.0.1.dist-info/top_level.txt
object_graph_streamer-0.0.1.dist-info/RECORD
